stsp/__init__.py
stsp/protocols/account/account.py
stsp/protocols/limits/limit.py
stsp/protocols/limits/models.py
stsp/protocols/models/common.py
stsp/protocols/position/close_position.py
stsp/protocols/position/models.py
stsp/protocols/position/open_position.py
stsp/protocols/predict/models.py
stsp/protocols/predict/prediction.py
stsp/protocols/risk/risk.py
stsp/protocols/strategy/strategy.py
stsp-0.1.1.dist-info/LICENSE
stsp-0.1.1.dist-info/METADATA
stsp-0.1.1.dist-info/WHEEL
stsp-0.1.1.dist-info/RECORD
